storpool_charms_manage-0.1.0-nspkg.pth
storpool/charms/manage/__init__.py
storpool/charms/manage/__main__.py
storpool/charms/manage/actions.py
storpool/charms/manage/charm.py
storpool/charms/manage/config.py
storpool/charms/manage/data.py
storpool/charms/manage/git.py
storpool/charms/manage/juju.py
storpool/charms/manage/py.typed
storpool/charms/manage/utils.py
storpool_charms_manage-0.1.0.dist-info/DESCRIPTION.rst
storpool_charms_manage-0.1.0.dist-info/METADATA
storpool_charms_manage-0.1.0.dist-info/RECORD
storpool_charms_manage-0.1.0.dist-info/WHEEL
storpool_charms_manage-0.1.0.dist-info/entry_points.txt
storpool_charms_manage-0.1.0.dist-info/metadata.json
storpool_charms_manage-0.1.0.dist-info/namespace_packages.txt
storpool_charms_manage-0.1.0.dist-info/top_level.txt
storpool_charms_manage-0.1.0.dist-info/zip-safe
