Metadata-Version: 2.0
Name: storpool-charms-manage
Version: 0.1.0
Summary: Build, deploy, and configure the StorPool Juju charms
Home-page: https://github.com/storpool/storpool-charms/
Author: Peter Pentchev
Author-email: openstack-dev@storpool.com
License: BSD-2
Platform: UNKNOWN
Classifier: Development Status :: 4 - Beta
Classifier: Intended Audience :: Developers
Classifier: License :: DFSG approved
Classifier: License :: Freely Distributable
Classifier: License :: OSI Approved :: Apache Software License
Classifier: Operating System :: POSIX
Classifier: Operating System :: Unix
Classifier: Programming Language :: Python
Classifier: Programming Language :: Python :: 3
Classifier: Programming Language :: Python :: 3.5
Classifier: Programming Language :: Python :: 3.6
Classifier: Programming Language :: Python :: 3.7
Classifier: Programming Language :: Python :: 3 :: Only
Classifier: Programming Language :: Python :: 3.5
Classifier: Topic :: Software Development :: Libraries
Classifier: Topic :: Software Development :: Libraries :: Python Modules
Classifier: Topic :: Utilities
Requires-Dist: PyYAML
Requires-Dist: mypy-extensions
